adb-1.2.0.dist-info/RECORD
adb-1.2.0.dist-info/METADATA
adb-1.2.0.dist-info/top_level.txt
adb-1.2.0.dist-info/metadata.json
adb-1.2.0.dist-info/DESCRIPTION.rst
adb-1.2.0.dist-info/WHEEL
adb/adb_commands.py
adb/fastboot_debug.py
adb/__init__.py
adb/common.py
adb/fastboot.py
adb/usb_exceptions.py
adb/filesync_protocol.py
adb/sign_pythonrsa.py
adb/adb_protocol.py
adb/common_cli.py
adb/sign_m2crypto.py
adb/adb_debug.py
